MATH/__init__.py
MATH/module.py
lemsmath_py-0.0.1.dist-info/licenses/LICENCE
lemsmath_py-0.0.1.dist-info/METADATA
lemsmath_py-0.0.1.dist-info/WHEEL
lemsmath_py-0.0.1.dist-info/top_level.txt
lemsmath_py-0.0.1.dist-info/RECORD
