Metadata-Version: 2.4
Name: lemsMath_py
Version: 0.0.1
Summary: package de verification
Home-page: 
Author: Lembou pharel
Author-email: lemboupharel@proton.me
License: MIT
Requires-Python: >=3.8
License-File: LICENCE
Dynamic: author
Dynamic: author-email
Dynamic: description-content-type
Dynamic: license
Dynamic: license-file
Dynamic: requires-python
Dynamic: summary
